subconscious/__init__.py
subconscious/column.py
subconscious/model.py
subconscious/query.py
subconscious-0.8.5.dist-info/DESCRIPTION.rst
subconscious-0.8.5.dist-info/METADATA
subconscious-0.8.5.dist-info/RECORD
subconscious-0.8.5.dist-info/WHEEL
subconscious-0.8.5.dist-info/metadata.json
subconscious-0.8.5.dist-info/top_level.txt
tests/__init__.py
tests/base.py
tests/test_all.py
tests/test_auto_int.py
tests/test_composite_key.py
tests/test_filter_by.py
tests/test_get_object_or_none.py
tests/test_order_by.py
tests/test_save_and_load.py
