Metadata-Version: 2.0
Name: subconscious
Version: 0.8.5
Summary: redis-backed db for python3 (asyncio compatible)
Home-page: https://github.com/paxos-bankchain/subconscious
Author: Paxos Trust Company, LLC
Author-email: pypi@paxos.com
License: MIT
Platform: UNKNOWN
Classifier: License :: OSI Approved :: MIT License
Classifier: Programming Language :: Python :: 3.6
Requires-Dist: aioredis
